Metadata-Version: 2.1
Name: kokokoako
Version: 1.0.0
Summary: Cool package.
Author: HW
Author-email: 
Classifier: Development Status :: 1 - Planning
Classifier: Intended Audience :: Developers
Classifier: Programming Language :: Python :: 3
Classifier: Operating System :: Unix
Classifier: Operating System :: MacOS :: MacOS X
Classifier: Operating System :: Microsoft :: Windows
